leap.soledad.server-0.9.6.post2-py2.7-nspkg.pth
leap/soledad/server/__init__.py
leap/soledad/server/_blobs.py
leap/soledad/server/_config.py
leap/soledad/server/_resource.py
leap/soledad/server/_server_info.py
leap/soledad/server/_version.py
leap/soledad/server/_wsgi.py
leap/soledad/server/auth.py
leap/soledad/server/caching.py
leap/soledad/server/entrypoint.py
leap/soledad/server/gzip_middleware.py
leap/soledad/server/interfaces.py
leap/soledad/server/session.py
leap/soledad/server/state.py
leap/soledad/server/sync.py
leap/soledad/server/url_mapper.py
leap.soledad.server-0.9.6.post2.dist-info/DESCRIPTION.rst
leap.soledad.server-0.9.6.post2.dist-info/METADATA
leap.soledad.server-0.9.6.post2.dist-info/RECORD
leap.soledad.server-0.9.6.post2.dist-info/WHEEL
leap.soledad.server-0.9.6.post2.dist-info/metadata.json
leap.soledad.server-0.9.6.post2.dist-info/namespace_packages.txt
leap.soledad.server-0.9.6.post2.dist-info/pbr.json
leap.soledad.server-0.9.6.post2.dist-info/top_level.txt
